MANIFEST.in
README.rst
setup.py
whereampy/__init__.py
whereampy/cli.py
whereampy/main.py
whereampy/mkpkg.py
whereampy/setup.py.template
whereampy.egg-info/PKG-INFO
whereampy.egg-info/SOURCES.txt
whereampy.egg-info/dependency_links.txt
whereampy.egg-info/entry_points.txt
whereampy.egg-info/top_level.txt