Metadata-Version: 1.0
Name: whereampy
Version: 0.4.5
Summary: Simple utility created as an example setuptools project.
Home-page: http://bitbucket.org/schmichael/whereampy/
Author: Michael Schurter
Author-email: michael@susens-schurter.com
License: Public Domain
Platform: UNKNOWN
